iceberg_cli/__init__.py
iceberg_cli/catalog.py
iceberg_cli/documentation.py
iceberg_cli/main.py
iceberg_cli/profiles.py
iceberg_cli/schema_parser.py
iceberg_cli/shell.py
iceberg_cli/sql.py
iceberg_cli/utils.py
iceberg_cli-0.1.0.dist-info/METADATA
iceberg_cli-0.1.0.dist-info/WHEEL
iceberg_cli-0.1.0.dist-info/entry_points.txt
iceberg_cli-0.1.0.dist-info/top_level.txt
iceberg_cli-0.1.0.dist-info/RECORD
